dpps/__init__.py
dpps/_version.py
ctao_dpps_clients-0.3.0.dist-info/METADATA
ctao_dpps_clients-0.3.0.dist-info/WHEEL
ctao_dpps_clients-0.3.0.dist-info/top_level.txt
ctao_dpps_clients-0.3.0.dist-info/RECORD
